lstm_forecast/__init__.py
lstm_forecast/cli.py
lstm_forecast/config.py
lstm_forecast/data_loader.py
lstm_forecast/early_stopping.py
lstm_forecast/feature_engineering.py
lstm_forecast/feature_selection.py
lstm_forecast/hyperparameter_optimization.py
lstm_forecast/logger.py
lstm_forecast/model.py
lstm_forecast/model_utils.py
lstm_forecast/predict.py
lstm_forecast/predict_utils.py
lstm_forecast/train.py
lstm_forecast/api/__init__.py
lstm_forecast/api/app.py
lstm_forecast/api/config.py
lstm_forecast/api/models.py
lstm_forecast/api/routes.py
lstm_forecast/api/utils.py
lstm_forecast/backtesting/__init__.py
lstm_forecast/backtesting/backtest.py
lstm_forecast/backtesting/metrics.py
lstm_forecast/backtesting/plot.py
lstm_forecast/backtesting/portfolio.py
lstm_forecast/backtesting/trading_engine.py
lstm_forecast-0.1.5.dist-info/LICENSE
lstm_forecast-0.1.5.dist-info/METADATA
lstm_forecast-0.1.5.dist-info/WHEEL
lstm_forecast-0.1.5.dist-info/entry_points.txt
lstm_forecast-0.1.5.dist-info/top_level.txt
lstm_forecast-0.1.5.dist-info/RECORD
