Metadata-Version: 2.1
Name: lstm-forecast
Version: 0.1.5
Summary: A package for LSTM-based financial time series forecasting
Home-page: https://github.com/gianlucamazza/lstm_forecast
Author: Gianluca Mazza
Author-email: gmazza1989@proton.me
License: MIT
Project-URL: Bug Tracker, https://github.com/gianlucamazza/lstm_forecast/issues
Project-URL: Documentation, https://gianlucamazza.github.io/lstm_forecast/
Project-URL: Source Code, https://github.com/gianlucamazza/lstm_forecast
Keywords: lstm forecasting finance timeseries deeplearning
Platform: UNKNOWN
Classifier: Development Status :: 4 - Beta
Classifier: Intended Audience :: Developers
Classifier: Intended Audience :: Science/Research
Classifier: Topic :: Scientific/Engineering :: Artificial Intelligence
Classifier: Topic :: Software Development :: Libraries :: Python Modules
Classifier: License :: OSI Approved :: MIT License
Classifier: Programming Language :: Python :: 3
Classifier: Programming Language :: Python :: 3.7
Classifier: Programming Language :: Python :: 3.8
Classifier: Programming Language :: Python :: 3.9
Classifier: Programming Language :: Python :: 3.10
Classifier: Operating System :: OS Independent
Requires-Python: >=3.7
License-File: LICENSE
Requires-Dist: pandas>=2.2.2
Requires-Dist: ta>=0.11.0
Requires-Dist: statsmodels>=0.14.2
Requires-Dist: numpy>=1.26.4
Requires-Dist: yfinance>=0.2.41
Requires-Dist: matplotlib>=3.9.1
Requires-Dist: torch>=2.4.0
Requires-Dist: plotly>=5.3.1
Requires-Dist: scikit-learn>=1.5.1
Requires-Dist: xgboost>=2.1.0
Requires-Dist: optuna>=3.6.1
Requires-Dist: onnxruntime>=1.18.1
Requires-Dist: onnx>=1.16.2
Requires-Dist: Flask>=3.0.3
Provides-Extra: dev
Requires-Dist: pytest>=8.3.2; extra == "dev"
Requires-Dist: sphinx>=7.4.7; extra == "dev"
Requires-Dist: twine>=5.1.1; extra == "dev"
Requires-Dist: black>=24.8.0; extra == "dev"
Requires-Dist: flake8>=7.1.1; extra == "dev"
Requires-Dist: pre-commit>=3.7.1; extra == "dev"
